LICENSE
MANIFEST.in
README.rst
setup.cfg
setup.py
artellapipe/__init__.py
artellapipe/tools/__init__.py
artellapipe/tools/shadersmanager/__init__.py
artellapipe/tools/shadersmanager/__logging__.ini
artellapipe/tools/shadersmanager/__version__.py
artellapipe/tools/shadersmanager/core/__init__.py
artellapipe/tools/shadersmanager/core/shadersmanager.py
artellapipe/tools/shadersmanager/resources/images/no_shaders_available.png
artellapipe/tools/shadersmanager/resources/images/shadersmanager_logo.png
artellapipe/tools/shadersmanager/widgets/__init__.py
artellapipe/tools/shadersmanager/widgets/assetsviewer.py
artellapipe/tools/shadersmanager/widgets/shaderexporter.py
artellapipe/tools/shadersmanager/widgets/shaderslibrary.py
artellapipe_tools_shadersmanager.egg-info/PKG-INFO
artellapipe_tools_shadersmanager.egg-info/SOURCES.txt
artellapipe_tools_shadersmanager.egg-info/dependency_links.txt
artellapipe_tools_shadersmanager.egg-info/not-zip-safe
artellapipe_tools_shadersmanager.egg-info/requires.txt
artellapipe_tools_shadersmanager.egg-info/top_level.txt
tests/__init__.py
tests/test_general.py