Metadata-Version: 2.1
Name: artellapipe-tools-shadersmanager
Version: 0.0.3
Summary: Tool to manage all shaders for an Artella project
Home-page: https://github.com/ArtellaPipe/artellapipe-tools-shadersmanager
Author: Tomas Poveda
Author-email: tpovedatd@gmail.com
License: MIT
Platform: UNKNOWN
Provides-Extra: test
Provides-Extra: dev
